Workbook

Sheet Dashboard
A1: REFUELER SHARE — FINANCIAL MODEL DASHBOARD
A2: KPIs pull live from the Projection sheet. Change assumptions → numbers update here.
A4: Paying subscribers at Month 36 | B4: ARR at Month 36 | C4: Monthly revenue at M36 | D4: Gross margin at M36
A5: =Projection!AK7 -> 8801 | B5: =Projection!AK14 -> 2281248 | C5: =Projection!AK13 -> 190104 | D5: =Projection!AK21 -> 0.91841476
A7: Monthly operating profit at M36 | B7: Cumulative P&L at Month 36 | C7: ARR vs £2.1M target at M36 | D7: Fixed costs per month
A8: =Projection!AK27 -> 165094.32 | B8: =Projection!AK28 -> 947722.4 | C8: =Projection!AK30 -> 1.0863086 | D8: =Projection!B16 -> 54.84
A11: MODEL PARAMETERS (SUMMARY)
A12: Tier pricing | B12: Creative Premium £12/mo | Production Max £24/mo
A13: Tier mix | B13: 80% Production Max / 20% Creative Premium
A14: Acquisition growth | B14: 18%/mo (base case = target scenario). Sensitivity: 14%→£648k ARR, 18%→£2.1M, 20%→£3.7M
A15: Monthly churn | B15: 3.0% of existing base
A16: Founder salary | B16: £5,000/mo from Month 25 (Oct 2028)
A17: First hire | B17: £4,500/mo when paying subs reach 100
A18: Fixed infra / month | B18: £54.84 (Cloudflare, Hetzner, Supabase free, Tuta, Mullvad, Claude, domain, Apple)
A19: £2.1M ARR target | B19: ~8,750 subscribers needed at blended ARPU £240
A20: Sensitivity sheet | B20: Vary acquisition growth (8%–25%/mo) and churn (1%–5%) to see range of outcomes
A21: Modelling revenue | B21: P&L shown — profit line includes salary + first hire from trigger points

Sheet Assumptions
A1: REFUELER SHARE — FINANCIAL MODEL | All GBP | Blue = editable input
A2: Model: Oct 2026 – Sep 2029 (36 months) | Growth model: new subscriber acquisition grows monthly, churn applied to base
A3: §1 PRICING
A4: Creative Premium — monthly price (£) | B4: 12 | C4: User-confirmed
A5: Production Max — monthly price (£) | B5: 24 | C5: User-confirmed
A7: §2 SUBSCRIBER GROWTH MODEL
A8: Model: new subscriber ACQUISITION starts at Month 1 target and grows at g%/mo. Churn applied to base each month.
A9: Month 1 new subscribers acquired | B9: 5 | C9: Post-btc++ Berlin conservative start
A10: Monthly growth in NEW acquisition (% of prior month acquis.) | B10: 0.18 | C10: 18%/mo growth in acquisition → ~8,800 subs by M36 at 3% churn = £2.1M ARR. See sensitivity.
A11: Monthly churn rate (% of existing base) | B11: 0.03 | C11: Mid-range SaaS benchmark 2–5%
A12: Note: 18%/mo means new-signup acquisitions compound monthly (5→6→7→...→43 new/mo at M12→218 new/mo at M24). Churn pulls against this. At 15%/mo you reach ~£648k ARR; at 18% you hit £2.1M; at 20% you reach £3.7M. Sensitivity sheet shows full range.
A14: §3 TIER & PAYMENT MIX
A15: Production Max share of paying subscribers | B15: 0.8 | C15: 80/20 — user-confirmed
A16: Creative Premium share | B16: 0.2 | C16: Complement of PM share
A17: Stripe share of payments | B17: 0.7 | C17: 70% Stripe / 30% Lightning initially
A18: Lightning share of payments | B18: 0.3 | C18: Complement
A20: §4 FIXED INFRASTRUCTURE COSTS
A21: Cloudflare Workers Paid (£/mo) | B21: 4 | C21: Workers + KV
A22: Cloudflare KV add-on (£/mo) | B22: 5 | C22: User-confirmed
A23: Hetzner CAX21 (£/mo) | B23: 5 | C23: €5.77 ≈ £5; phoenixd + LNbits
A24: Supabase (£/mo) | B24: 0 | C24: Free tier — billing ledger only
A25: Tutamail (£/mo) | B25: 7 | C25: User-confirmed
A26: Mullvad VPN (£/mo) | B26: 5 | C26: User-confirmed
A27: Claude AI (£/mo) | B27: 18 | C27: User-confirmed
A28: Domain + hosting (£/mo equiv) | B28: 4.17 | C28: $50/yr ÷ 12
A29: Apple Dev Programme (£/mo equiv) | B29: 6.67 | C29: £80/yr ÷ 12
A31: §5 VARIABLE COSTS PER SUBSCRIBER (REALISTIC)
A32: Creative Premium infra cost/user/mo (£, incl. Stripe) | B32: 0.62 | C32: Per briefing
A33: Production Max infra cost/user/mo (£, incl. Stripe) | B33: 2.04 | C33: Per briefing
A35: §6 FOUNDER SALARY
A36: Founder salary start (month number, 1–36) | B36: 25 | C36: Month 25 = Oct 2028
A37: Founder monthly salary (£) | B37: 5000 | C37: £60k/yr — user-confirmed
A39: §7 FIRST HIRE
A40: First hire trigger — paying subscriber count | B40: 100 | C40: User-confirmed
A41: First hire monthly cost (£, all-in) | B41: 4500 | C41: Placeholder — update when real
A43: §8 TARGETS
A44: ARR target (£) | B44: 2100000 | C44: User-confirmed
A45: Subscriber count at target ARR | B45: 8750 | C45: 80/20 blend implies ~£240 ARPU

Sheet Projection
A1: REFUELER SHARE — 36-MONTH PROJECTION (Oct 2026 – Sep 2029)
B2: Oct-26 | C2: Nov-26 | D2: Dec-26 | E2: Jan-27 | F2: Feb-27 | G2: Mar-27 | H2: Apr-27 | I2: May-27 | J2: Jun-27 | K2: Jul-27 | L2: Aug-27 | M2: Sep-27 | N2: Oct-27 | O2: Nov-27 | P2: Dec-27 | Q2: Jan-28 | R2: Feb-28 | S2: Mar-28 | T2: Apr-28 | U2: May-28 | V2: Jun-28 | W2: Jul-28 | X2: Aug-28 | Y2: Sep-28 | Z2: Oct-28 | AA2: Nov-28 | AB2: Dec-28 | AC2: Jan-29 | AD2: Feb-29 | AE2: Mar-29 | AF2: Apr-29 | AG2: May-29 | AH2: Jun-29 | AI2: Jul-29 | AJ2: Aug-29 | AK2: Sep-29
A3: Month # | B3: 1 | C3: 2 | D3: 3 | E3: 4 | F3: 5 | G3: 6 | H3: 7 | I3: 8 | J3: 9 | K3: 10 | L3: 11 | M3: 12 | N3: 13 | O3: 14 | P3: 15 | Q3: 16 | R3: 17 | S3: 18 | T3: 19 | U3: 20 | V3: 21 | W3: 22 | X3: 23 | Y3: 24 | Z3: 25 | AA3: 26 | AB3: 27 | AC3: 28 | AD3: 29 | AE3: 30 | AF3: 31 | AG3: 32 | AH3: 33 | AI3: 34 | AJ3: 35 | AK3: 36
A4: §1 SUBSCRIBERS
A5: New subscriber acquisition (this month) | B5: =Assumptions!B9 -> 5 | C5: =ROUND(B5*(1+Assumptions!B10),0) -> 6 | D5: =ROUND(C5*(1+Assumptions!B10),0) -> 7 | E5: =ROUND(D5*(1+Assumptions!B10),0) -> 8 | F5: =ROUND(E5*(1+Assumptions!B10),0) -> 9 | G5: =ROUND(F5*(1+Assumptions!B10),0) -> 11 | H5: =ROUND(G5*(1+Assumptions!B10),0) -> 13 | I5: =ROUND(H5*(1+Assumptions!B10),0) -> 15 | J5: =ROUND(I5*(1+Assumptions!B10),0) -> 18 | K5: =ROUND(J5*(1+Assumptions!B10),0) -> 21 | L5: =ROUND(K5*(1+Assumptions!B10),0) -> 25 | M5: =ROUND(L5*(1+Assumptions!B10),0) -> 30 | N5: =ROUND(M5*(1+Assumptions!B10),0) -> 35 | O5: =ROUND(N5*(1+Assumptions!B10),0) -> 41 | P5: =ROUND(O5*(1+Assumptions!B10),0) -> 48 | Q5: =ROUND(P5*(1+Assumptions!B10),0) -> 57 | R5: =ROUND(Q5*(1+Assumptions!B10),0) -> 67 | S5: =ROUND(R5*(1+Assumptions!B10),0) -> 79 | T5: =ROUND(S5*(1+Assumptions!B10),0) -> 93 | U5: =ROUND(T5*(1+Assumptions!B10),0) -> 110 | V5: =ROUND(U5*(1+Assumptions!B10),0) -> 130 | W5: =ROUND(V5*(1+Assumptions!B10),0) -> 153 | X5: =ROUND(W5*(1+Assumptions!B10),0) -> 181 | Y5: =ROUND(X5*(1+Assumptions!B10),0) -> 214 | Z5: =ROUND(Y5*(1+Assumptions!B10),0) -> 253 | AA5: =ROUND(Z5*(1+Assumptions!B10),0) -> 299 | AB5: =ROUND(AA5*(1+Assumptions!B10),0) -> 353 | AC5: =ROUND(AB5*(1+Assumptions!B10),0) -> 417 | AD5: =ROUND(AC5*(1+Assumptions!B10),0) -> 492 | AE5: =ROUND(AD5*(1+Assumptions!B10),0) -> 581 | AF5: =ROUND(AE5*(1+Assumptions!B10),0) -> 686 | AG5: =ROUND(AF5*(1+Assumptions!B10),0) -> 809 | AH5: =ROUND(AG5*(1+Assumptions!B10),0) -> 955 | AI5: =ROUND(AH5*(1+Assumptions!B10),0) -> 1127 | AJ5: =ROUND(AI5*(1+Assumptions!B10),0) -> 1330 | AK5: =ROUND(AJ5*(1+Assumptions!B10),0) -> 1569
A6: Churned from existing base | B6: =0 -> 0 | C6: =ROUND(B7*Assumptions!B11,0) -> 0 | D6: =ROUND(C7*Assumptions!B11,0) -> 0 | E6: =ROUND(D7*Assumptions!B11,0) -> 1 | F6: =ROUND(E7*Assumptions!B11,0) -> 1 | G6: =ROUND(F7*Assumptions!B11,0) -> 1 | H6: =ROUND(G7*Assumptions!B11,0) -> 1 | I6: =ROUND(H7*Assumptions!B11,0) -> 2 | J6: =ROUND(I7*Assumptions!B11,0) -> 2 | K6: =ROUND(J7*Assumptions!B11,0) -> 3 | L6: =ROUND(K7*Assumptions!B11,0) -> 3 | M6: =ROUND(L7*Assumptions!B11,0) -> 4 | N6: =ROUND(M7*Assumptions!B11,0) -> 5 | O6: =ROUND(N7*Assumptions!B11,0) -> 5 | P6: =ROUND(O7*Assumptions!B11,0) -> 6 | Q6: =ROUND(P7*Assumptions!B11,0) -> 8 | R6: =ROUND(Q7*Assumptions!B11,0) -> 9 | S6: =ROUND(R7*Assumptions!B11,0) -> 11 | T6: =ROUND(S7*Assumptions!B11,0) -> 13 | U6: =ROUND(T7*Assumptions!B11,0) -> 15 | V6: =ROUND(U7*Assumptions!B11,0) -> 18 | W6: =ROUND(V7*Assumptions!B11,0) -> 22 | X6: =ROUND(W7*Assumptions!B11,0) -> 26 | Y6: =ROUND(X7*Assumptions!B11,0) -> 30 | Z6: =ROUND(Y7*Assumptions!B11,0) -> 36 | AA6: =ROUND(Z7*Assumptions!B11,0) -> 42 | AB6: =ROUND(AA7*Assumptions!B11,0) -> 50 | AC6: =ROUND(AB7*Assumptions!B11,0) -> 59 | AD6: =ROUND(AC7*Assumptions!B11,0) -> 70 | AE6: =ROUND(AD7*Assumptions!B11,0) -> 82 | AF6: =ROUND(AE7*Assumptions!B11,0) -> 97 | AG6: =ROUND(AF7*Assumptions!B11,0) -> 115 | AH6: =ROUND(AG7*Assumptions!B11,0) -> 136 | AI6: =ROUND(AH7*Assumptions!B11,0) -> 160 | AJ6: =ROUND(AI7*Assumptions!B11,0) -> 189 | AK6: =ROUND(AJ7*Assumptions!B11,0) -> 224
A7: Total paying subscribers (EOM) | B7: =MAX(0,B5) -> 5 | C7: =MAX(0,B7+C5-C6) -> 11 | D7: =MAX(0,C7+D5-D6) -> 18 | E7: =MAX(0,D7+E5-E6) -> 25 | F7: =MAX(0,E7+F5-F6) -> 33 | G7: =MAX(0,F7+G5-G6) -> 43 | H7: =MAX(0,G7+H5-H6) -> 55 | I7: =MAX(0,H7+I5-I6) -> 68 | J7: =MAX(0,I7+J5-J6) -> 84 | ... AK7: =MAX(0,AJ7+AK5-AK6) -> 8801
A8: → Production Max | B8: =ROUND(B7*Assumptions!B15,0) -> 4 | C8: =ROUND(C7*Assumptions!B15,0) -> 9 | D8: =ROUND(D7*Assumptions!B15,0) -> 14 | E8: =ROUND(E7*Assumptions!B15,0) -> 20 | F8: =ROUND(F7*Assumptions!B15,0) -> 26 | G8: =ROUND(G7*Assumptions!B15,0) -> 34 | H8: =ROUND(H7*Assumptions!B15,0) -> 44 | I8: =ROUND(I7*Assumptions!B15,0) -> 54 | J8: =ROUND(J7*Assumptions!B15,0) -> 67 | K8: =ROUND(K7*Assumptions!B15,0) -> 82 | L8: =ROUND(L7*Assumptions!B15,0) -> 99 | M8: =ROUND(M7*Assumptions!B15,0) -> 120 | N8: =ROUND(N7*Assumptions!B15,0) -> 144 | O8: =ROUND(O7*Assumptions!B15,0) -> 173 | P8: =ROUND(P7*Assumptions!B15,0) -> 206 | Q8: =ROUND(Q7*Assumptions!B15,0) -> 246 | R8: =ROUND(R7*Assumptions!B15,0) -> 292 | S8: =ROUND(S7*Assumptions!B15,0) -> 346 | T8: =ROUND(T7*Assumptions!B15,0) -> 410 | U8: =ROUND(U7*Assumptions!B15,0) -> 486 | V8: =ROUND(V7*Assumptions!B15,0) -> 576 | W8: =ROUND(W7*Assumptions!B15,0) -> 681 | X8: =ROUND(X7*Assumptions!B15,0) -> 805 | Y8: =ROUND(Y7*Assumptions!B15,0) -> 952 | Z8: =ROUND(Z7*Assumptions!B15,0) -> 1126 | AA8: =ROUND(AA7*Assumptions!B15,0) -> 1331 | AB8: =ROUND(AB7*Assumptions!B15,0) -> 1574 | AC8: =ROUND(AC7*Assumptions!B15,0) -> 1860 | AD8: =ROUND(AD7*Assumptions!B15,0) -> 2198 | AE8: =ROUND(AE7*Assumptions!B15,0) -> 2597 | AF8: =ROUND(AF7*Assumptions!B15,0) -> 3068 | AG8: =ROUND(AG7*Assumptions!B15,0) -> 3623 | AH8: =ROUND(AH7*Assumptions!B15,0) -> 4278 | AI8: =ROUND(AI7*Assumptions!B15,0) -> 5052 | AJ8: =ROUND(AJ7*Assumptions!B15,0) -> 5965 | AK8: =ROUND(AK7*Assumptions!B15,0) -> 7041
A9: → Creative Premium | B9: =MAX(0,B7-B8) -> 1 | C9: =MAX(0,C7-C8) -> 2 | D9: =MAX(0,D7-D8) -> 4 | E9: =MAX(0,E7-E8) -> 5 | F9: =MAX(0,F7-F8) -> 7 | G9: =MAX(0,G7-G8) -> 9 | H9: =MAX(0,H7-H8) -> 11 | I9: =MAX(0,I7-I8) -> 14 | ... AK9: =MAX(0,AK7-AK8) -> 1760
A10: §2 REVENUE
A11: Production Max (£) | B11: =B8*Assumptions!B5 -> 96 | C11: =C8*Assumptions!B5 -> 216 | D11: =D8*Assumptions!B5 -> 336 | E11: =E8*Assumptions!B5 -> 480 | F11: =F8*Assumptions!B5 -> 624 | G11: =G8*Assumptions!B5 -> 816 | H11: =H8*Assumptions!B5 -> 1056 | I11: =I8*Assumptions!B5 -> 1296 | J11: =J8*Assumptions!B5 -> 1608 | K11: =K8*Assumptions!B5 -> 1968 | L11: =L8*Assumptions!B5 -> 2376 | M11: =M8*Assumptions!B5 -> 2880 | N11: =N8*Assumptions!B5 -> 3456 | O11: =O8*Assumptions!B5 -> 4152 | P11: =P8*Assumptions!B5 -> 4944 | Q11: =Q8*Assumptions!B5 -> 5904 | R11: =R8*Assumptions!B5 -> 7008 | S11: =S8*Assumptions!B5 -> 8304 | T11: =T8*Assumptions!B5 -> 9840 | U11: =U8*Assumptions!B5 -> 11664 | V11: =V8*Assumptions!B5 -> 13824 | W11: =W8*Assumptions!B5 -> 16344 | X11: =X8*Assumptions!B5 -> 19320 | Y11: =Y8*Assumptions!B5 -> 22848 | Z11: =Z8*Assumptions!B5 -> 27024 | AA11: =AA8*Assumptions!B5 -> 31944 | AB11: =AB8*Assumptions!B5 -> 37776 | AC11: =AC8*Assumptions!B5 -> 44640 | AD11: =AD8*Assumptions!B5 -> 52752 | AE11: =AE8*Assumptions!B5 -> 62328 | AF11: =AF8*Assumptions!B5 -> 73632 | AG11: =AG8*Assumptions!B5 -> 86952 | AH11: =AH8*Assumptions!B5 -> 102672 | AI11: =AI8*Assumptions!B5 -> 121248 | AJ11: =AJ8*Assumptions!B5 -> 143160 | AK11: =AK8*Assumptions!B5 -> 168984
A12: Creative Premium (£) | B12: =B9*Assumptions!B4 -> 12 | C12: =C9*Assumptions!B4 -> 24 | D12: =D9*Assumptions!B4 -> 48 | E12: =E9*Assumptions!B4 -> 60 | F12: =F9*Assumptions!B4 -> 84 | G12: =G9*Assumptions!B4 -> 108 | H12: =H9*Assumptions!B4 -> 132 | I12: =I9*Assumptions!B4 -> 168 | J12: =J9*Assumptions!B4 -> 204 | K12: =K9*Assumptions!B4 -> 240 | L12: =L9*Assumptions!B4 -> 300 | M12: =M9*Assumptions!B4 -> 360 | N12: =N9*Assumptions!B4 -> 432 | O12: =O9*Assumptions!B4 -> 516 | P12: =P9*Assumptions!B4 -> 624 | Q12: =Q9*Assumptions!B4 -> 732 | R12: =R9*Assumptions!B4 -> 876 | S12: =S9*Assumptions!B4 -> 1044 | T12: =T9*Assumptions!B4 -> 1236 | U12: =U9*Assumptions!B4 -> 1464 | V12: =V9*Assumptions!B4 -> 1728 | W12: =W9*Assumptions!B4 -> 2040 | X12: =X9*Assumptions!B4 -> 2412 | Y12: =Y9*Assumptions!B4 -> 2856 | Z12: =Z9*Assumptions!B4 -> 3372 | AA12: =AA9*Assumptions!B4 -> 3996 | AB12: =AB9*Assumptions!B4 -> 4716 | AC12: =AC9*Assumptions!B4 -> 5580 | AD12: =AD9*Assumptions!B4 -> 6588 | AE12: =AE9*Assumptions!B4 -> 7788 | AF12: =AF9*Assumptions!B4 -> 9204 | AG12: =AG9*Assumptions!B4 -> 10872 | AH12: =AH9*Assumptions!B4 -> 12840 | AI12: =AI9*Assumptions!B4 -> 15156 | AJ12: =AJ9*Assumptions!B4 -> 17892 | AK12: =AK9*Assumptions!B4 -> 21120
A13: Total monthly revenue (£) | B13: =B11+B12 -> 108 | C13: =C11+C12 -> 240 | D13: =D11+D12 -> 384 | E13: =E11+E12 -> 540 | F13: =F11+F12 -> 708 | G13: =G11+G12 -> 924 | H13: =H11+H12 -> 1188 | I13: =I11+I12 -> 1464 | ... AK13: =AK11+AK12 -> 190104
A14: → ARR run-rate (£) | B14: =B13*12 -> 1296 | C14: =C13*12 -> 2880 | D14: =D13*12 -> 4608 | E14: =E13*12 -> 6480 | F14: =F13*12 -> 8496 | G14: =G13*12 -> 11088 | H14: =H13*12 -> 14256 | I14: =I13*12 -> 17568 | ... AK14: =AK13*12 -> 2281248
A15: §3 GROSS PROFIT
A16: Fixed infra (£/mo) | B16: =Assumptions!B21+Assumptions!B22+Assumptions!B23+Assumptions!B24+Assumptions!B25+Assumptions!B26+Assumptions!B27+Assumptions!B28+Assumptions!B29 -> 54.84 | C16: =Assumptions!B21+Assumptions!B22+Assumptions!B23+Assumptions!B24+Assumptions!B25+Assumptions!B26+Assumptions!B27+Assumptions!B28+Assumptions!B29 -> 54.84 | D16: =Assumptions!B21+Assumptions!B22+Assumptions!B23+Assumptions!B24+Assumptions!B25+Assumptions!B26+Assumptions!B27+Assumptions!B28+Assumptions!B29 -> 54.84 | E16: =Assumptions!B21+Assumptions!B22+Assumptions!B23+Assumptions!B24+Assumptions!B25+Assumptions!B26+Assumptions!B27+Assumptions!B28+Assumptions!B29 -> 54.84 | F16: =Assumptions!B21+Assumptions!B22+Assumptions!B23+Assumptions!B24+Assumptions!B25+Assumptions!B26+Assumptions!B27+Assumptions!B28+Assumptions!B29 -> 54.84 | G16: =Assumptions!B21+Assumptions!B22+Assumptions!B23+Assumptions!B24+Assumptions!B25+Assumptions!B26+Assumptions!B27+Assumptions!B28+Assumptions!B29 -> 54.84 | H16: =Assumptions!B21+Assumptions!B22+Assumptions!B23+Assumptions!B24+Assumptions!B25+Assumptions!B26+Assumptions!B27+Assumptions!B28+Assumptions!B29 -> 54.84 | I16: =Assumptions!B21+Assumptions!B22+Assumptions!B23+Assumptions!B24+Assumptions!B25+Assumptions!B26+Assumptions!B27+Assumptions!B28+Assumptions!B29 -> 54.84 | J16: =Assumptions!B21+Assumptions!B22+Assumptions!B23+Assumptions!B24+Assumptions!B25+Assumptions!B26+Assumptions!B27+Assumptions!B28+Assumptions!B29 -> 54.84 | K16: =Assumptions!B21+Assumptions!B22+Assumptions!B23+Assumptions!B24+Assumptions!B25+Assumptions!B26+Assumptions!B27+Assumptions!B28+Assumptions!B29 -> 54.84 | L16: =Assumptions!B21+Assumptions!B22+Assumptions!B23+Assumptions!B24+Assumptions!B25+Assumptions!B26+Assumptions!B27+Assumptions!B28+Assumptions!B29 -> 54.84 | M16: =Assumptions!B21+Assumptions!B22+Assumptions!B23+Assumptions!B24+Assumptions!B25+Assumptions!B26+Assumptions!B27+Assumptions!B28+Assumptions!B29 -> 54.84 | N16: =Assumptions!B21+Assumptions!B22+Assumptions!B23+Assumptions!B24+Assumptions!B25+Assumptions!B26+Assumptions!B27+Assumptions!B28+Assumptions!B29 -> 54.84 | O16: =Assumptions!B21+Assumptions!B22+Assumptions!B23+Assumptions!B24+Assumptions!B25+Assumptions!B26+Assumptions!B27+Assumptions!B28+Assumptions!B29 -> 54.84 | P16: =Assumptions!B21+Assumptions!B22+Assumptions!B23+Assumptions!B24+Assumptions!B25+Assumptions!B26+Assumptions!B27+Assumptions!B28+Assumptions!B29 -> 54.84 | Q16: =Assumptions!B21+Assumptions!B22+Assumptions!B23+Assumptions!B24+Assumptions!B25+Assumptions!B26+Assumptions!B27+Assumptions!B28+Assumptions!B29 -> 54.84 | R16: =Assumptions!B21+Assumptions!B22+Assumptions!B23+Assumptions!B24+Assumptions!B25+Assumptions!B26+Assumptions!B27+Assumptions!B28+Assumptions!B29 -> 54.84 | S16: =Assumptions!B21+Assumptions!B22+Assumptions!B23+Assumptions!B24+Assumptions!B25+Assumptions!B26+Assumptions!B27+Assumptions!B28+Assumptions!B29 -> 54.84 | T16: =Assumptions!B21+Assumptions!B22+Assumptions!B23+Assumptions!B24+Assumptions!B25+Assumptions!B26+Assumptions!B27+Assumptions!B28+Assumptions!B29 -> 54.84 | U16: =Assumptions!B21+Assumptions!B22+Assumptions!B23+Assumptions!B24+Assumptions!B25+Assumptions!B26+Assumptions!B27+Assumptions!B28+Assumptions!B29 -> 54.84 | V16: =Assumptions!B21+Assumptions!B22+Assumptions!B23+Assumptions!B24+Assumptions!B25+Assumptions!B26+Assumptions!B27+Assumptions!B28+Assumptions!B29 -> 54.84 | W16: =Assumptions!B21+Assumptions!B22+Assumptions!B23+Assumptions!B24+Assumptions!B25+Assumptions!B26+Assumptions!B27+Assumptions!B28+Assumptions!B29 -> 54.84 | X16: =Assumptions!B21+Assumptions!B22+Assumptions!B23+Assumptions!B24+Assumptions!B25+Assumptions!B26+Assumptions!B27+Assumptions!B28+Assumptions!B29 -> 54.84 | Y16: =Assumptions!B21+Assumptions!B22+Assumptions!B23+Assumptions!B24+Assumptions!B25+Assumptions!B26+Assumptions!B27+Assumptions!B28+Assumptions!B29 -> 54.84 | Z16: =Assumptions!B21+Assumptions!B22+Assumptions!B23+Assumptions!B24+Assumptions!B25+Assumptions!B26+Assumptions!B27+Assumptions!B28+Assumptions!B29 -> 54.84 | AA16: =Assumptions!B21+Assumptions!B22+Assumptions!B23+Assumptions!B24+Assumptions!B25+Assumptions!B26+Assumptions!B27+Assumptions!B28+Assumptions!B29 -> 54.84 | AB16: =Assumptions!B21+Assumptions!B22+Assumptions!B23+Assumptions!B24+Assumptions!B25+Assumptions!B26+Assumptions!B27+Assumptions!B28+Assumptions!B29 -> 54.84 | AC16: =Assumptions!B21+Assumptions!B22+Assumptions!B23+Assumptions!B24+Assumptions!B25+Assumptions!B26+Assumptions!B27+Assumptions!B28+Assumptions!B29 -> 54.84 | AD16: =Assumptions!B21+Assumptions!B22+Assumptions!B23+Assumptions!B24+Assumptions!B25+Assumptions!B26+Assumptions!B27+Assumptions!B28+Assumptions!B29 -> 54.84 | AE16: =Assumptions!B21+Assumptions!B22+Assumptions!B23+Assumptions!B24+Assumptions!B25+Assumptions!B26+Assumptions!B27+Assumptions!B28+Assumptions!B29 -> 54.84 | AF16: =Assumptions!B21+Assumptions!B22+Assumptions!B23+Assumptions!B24+Assumptions!B25+Assumptions!B26+Assumptions!B27+Assumptions!B28+Assumptions!B29 -> 54.84 | AG16: =Assumptions!B21+Assumptions!B22+Assumptions!B23+Assumptions!B24+Assumptions!B25+Assumptions!B26+Assumptions!B27+Assumptions!B28+Assumptions!B29 -> 54.84 | AH16: =Assumptions!B21+Assumptions!B22+Assumptions!B23+Assumptions!B24+Assumptions!B25+Assumptions!B26+Assumptions!B27+Assumptions!B28+Assumptions!B29 -> 54.84 | AI16: =Assumptions!B21+Assumptions!B22+Assumptions!B23+Assumptions!B24+Assumptions!B25+Assumptions!B26+Assumptions!B27+Assumptions!B28+Assumptions!B29 -> 54.84 | AJ16: =Assumptions!B21+Assumptions!B22+Assumptions!B23+Assumptions!B24+Assumptions!B25+Assumptions!B26+Assumptions!B27+Assumptions!B28+Assumptions!B29 -> 54.84 | AK16: =Assumptions!B21+Assumptions!B22+Assumptions!B23+Assumptions!B24+Assumptions!B25+Assumptions!B26+Assumptions!B27+Assumptions!B28+Assumptions!B29 -> 54.84
A17: Variable — PM users (£) | B17: =B8*Assumptions!B33 -> 8.16 | C17: =C8*Assumptions!B33 -> 18.36 | D17: =D8*Assumptions!B33 -> 28.56 | E17: =E8*Assumptions!B33 -> 40.8 | F17: =F8*Assumptions!B33 -> 53.04 | G17: =G8*Assumptions!B33 -> 69.36 | H17: =H8*Assumptions!B33 -> 89.76 | I17: =I8*Assumptions!B33 -> 110.16 | J17: =J8*Assumptions!B33 -> 136.68 | K17: =K8*Assumptions!B33 -> 167.28 | L17: =L8*Assumptions!B33 -> 201.96 | M17: =M8*Assumptions!B33 -> 244.8 | N17: =N8*Assumptions!B33 -> 293.76 | O17: =O8*Assumptions!B33 -> 352.92 | P17: =P8*Assumptions!B33 -> 420.24 | Q17: =Q8*Assumptions!B33 -> 501.84 | R17: =R8*Assumptions!B33 -> 595.68 | S17: =S8*Assumptions!B33 -> 705.84 | T17: =T8*Assumptions!B33 -> 836.4 | U17: =U8*Assumptions!B33 -> 991.44 | V17: =V8*Assumptions!B33 -> 1175.04 | W17: =W8*Assumptions!B33 -> 1389.24 | X17: =X8*Assumptions!B33 -> 1642.2 | Y17: =Y8*Assumptions!B33 -> 1942.08 | Z17: =Z8*Assumptions!B33 -> 2297.04 | AA17: =AA8*Assumptions!B33 -> 2715.24 | AB17: =AB8*Assumptions!B33 -> 3210.96 | AC17: =AC8*Assumptions!B33 -> 3794.4 | AD17: =AD8*Assumptions!B33 -> 4483.92 | AE17: =AE8*Assumptions!B33 -> 5297.88 | AF17: =AF8*Assumptions!B33 -> 6258.72 | AG17: =AG8*Assumptions!B33 -> 7390.92 | AH17: =AH8*Assumptions!B33 -> 8727.12 | AI17: =AI8*Assumptions!B33 -> 10306.08 | AJ17: =AJ8*Assumptions!B33 -> 12168.6 | AK17: =AK8*Assumptions!B33 -> 14363.64
A18: Variable — CP users (£) | B18: =B9*Assumptions!B32 -> 0.62 | C18: =C9*Assumptions!B32 -> 1.24 | D18: =D9*Assumptions!B32 -> 2.48 | E18: =E9*Assumptions!B32 -> 3.1 | F18: =F9*Assumptions!B32 -> 4.34 | G18: =G9*Assumptions!B32 -> 5.58 | H18: =H9*Assumptions!B32 -> 6.82 | I18: =I9*Assumptions!B32 -> 8.68 | J18: =J9*Assumptions!B32 -> 10.54 | K18: =K9*Assumptions!B32 -> 12.4 | L18: =L9*Assumptions!B32 -> 15.5 | M18: =M9*Assumptions!B32 -> 18.6 | N18: =N9*Assumptions!B32 -> 22.32 | O18: =O9*Assumptions!B32 -> 26.66 | P18: =P9*Assumptions!B32 -> 32.24 | Q18: =Q9*Assumptions!B32 -> 37.82 | R18: =R9*Assumptions!B32 -> 45.26 | S18: =S9*Assumptions!B32 -> 53.94 | T18: =T9*Assumptions!B32 -> 63.86 | U18: =U9*Assumptions!B32 -> 75.64 | V18: =V9*Assumptions!B32 -> 89.28 | W18: =W9*Assumptions!B32 -> 105.4 | X18: =X9*Assumptions!B32 -> 124.62 | Y18: =Y9*Assumptions!B32 -> 147.56 | Z18: =Z9*Assumptions!B32 -> 174.22 | AA18: =AA9*Assumptions!B32 -> 206.46 | AB18: =AB9*Assumptions!B32 -> 243.66 | AC18: =AC9*Assumptions!B32 -> 288.3 | AD18: =AD9*Assumptions!B32 -> 340.38 | AE18: =AE9*Assumptions!B32 -> 402.38 | AF18: =AF9*Assumptions!B32 -> 475.54 | AG18: =AG9*Assumptions!B32 -> 561.72 | AH18: =AH9*Assumptions!B32 -> 663.4 | AI18: =AI9*Assumptions!B32 -> 783.06 | AJ18: =AJ9*Assumptions!B32 -> 924.42 | AK18: =AK9*Assumptions!B32 -> 1091.2
A19: Total COGS (£) | B19: =B16+B17+B18 -> 63.62 | C19: =C16+C17+C18 -> 74.44 | D19: =D16+D17+D18 -> 85.88 | E19: =E16+E17+E18 -> 98.74 | F19: =F16+F17+F18 -> 112.22 | G19: =G16+G17+G18 -> 129.78 | H19: =H16+H17+H18 -> 151.42 | I19: =I16+I17+I18 -> 173.68 | ... AK19: =AK16+AK17+AK18 -> 15509.68
A20: Gross profit (£) | B20: =B13-B19 -> 44.38 | C20: =C13-C19 -> 165.56 | D20: =D13-D19 -> 298.12 | E20: =E13-E19 -> 441.26 | F20: =F13-F19 -> 595.78 | G20: =G13-G19 -> 794.22 | H20: =H13-H19 -> 1036.58 | I20: =I13-I19 -> 1290.32 | ... AK20: =AK13-AK19 -> 174594.32
A21: Gross margin % | B21: =IFERROR(B20/B13,0) -> 0.41092593 | C21: =IFERROR(C20/C13,0) -> 0.68983333 | D21: =IFERROR(D20/D13,0) -> 0.77635417 | E21: =IFERROR(E20/E13,0) -> 0.81714815 | F21: =IFERROR(F20/F13,0) -> 0.84149718 | G21: =IFERROR(G20/G13,0) -> 0.85954545 | H21: =IFERROR(H20/H13,0) -> 0.87254209 | I21: =IFERROR(I20/I13,0) -> 0.88136612 | ... AK21: =IFERROR(AK20/AK13,0) -> 0.91841476
A22: §4 OPEX
A23: Founder salary (£/mo, from trigger month) | B23: =IF(1>=Assumptions!B36,Assumptions!B37,0) -> 0 | C23: =IF(2>=Assumptions!B36,Assumptions!B37,0) -> 0 | D23: =IF(3>=Assumptions!B36,Assumptions!B37,0) -> 0 | E23: =IF(4>=Assumptions!B36,Assumptions!B37,0) -> 0 | F23: =IF(5>=Assumptions!B36,Assumptions!B37,0) -> 0 | G23: =IF(6>=Assumptions!B36,Assumptions!B37,0) -> 0 | H23: =IF(7>=Assumptions!B36,Assumptions!B37,0) -> 0 | I23: =IF(8>=Assumptions!B36,Assumptions!B37,0) -> 0 | J23: =IF(9>=Assumptions!B36,Assumptions!B37,0) -> 0 | K23: =IF(10>=Assumptions!B36,Assumptions!B37,0) -> 0 | L23: =IF(11>=Assumptions!B36,Assumptions!B37,0) -> 0 | M23: =IF(12>=Assumptions!B36,Assumptions!B37,0) -> 0 | N23: =IF(13>=Assumptions!B36,Assumptions!B37,0) -> 0 | O23: =IF(14>=Assumptions!B36,Assumptions!B37,0) -> 0 | P23: =IF(15>=Assumptions!B36,Assumptions!B37,0) -> 0 | Q23: =IF(16>=Assumptions!B36,Assumptions!B37,0) -> 0 | R23: =IF(17>=Assumptions!B36,Assumptions!B37,0) -> 0 | S23: =IF(18>=Assumptions!B36,Assumptions!B37,0) -> 0 | T23: =IF(19>=Assumptions!B36,Assumptions!B37,0) -> 0 | U23: =IF(20>=Assumptions!B36,Assumptions!B37,0) -> 0 | V23: =IF(21>=Assumptions!B36,Assumptions!B37,0) -> 0 | W23: =IF(22>=Assumptions!B36,Assumptions!B37,0) -> 0 | X23: =IF(23>=Assumptions!B36,Assumptions!B37,0) -> 0 | Y23: =IF(24>=Assumptions!B36,Assumptions!B37,0) -> 0 | Z23: =IF(25>=Assumptions!B36,Assumptions!B37,0) -> 5000 | AA23: =IF(26>=Assumptions!B36,Assumptions!B37,0) -> 5000 | AB23: =IF(27>=Assumptions!B36,Assumptions!B37,0) -> 5000 | AC23: =IF(28>=Assumptions!B36,Assumptions!B37,0) -> 5000 | AD23: =IF(29>=Assumptions!B36,Assumptions!B37,0) -> 5000 | AE23: =IF(30>=Assumptions!B36,Assumptions!B37,0) -> 5000 | AF23: =IF(31>=Assumptions!B36,Assumptions!B37,0) -> 5000 | AG23: =IF(32>=Assumptions!B36,Assumptions!B37,0) -> 5000 | AH23: =IF(33>=Assumptions!B36,Assumptions!B37,0) -> 5000 | AI23: =IF(34>=Assumptions!B36,Assumptions!B37,0) -> 5000 | AJ23: =IF(35>=Assumptions!B36,Assumptions!B37,0) -> 5000 | AK23: =IF(36>=Assumptions!B36,Assumptions!B37,0) -> 5000
A24: First hire (£/mo, from trigger subscriber count) | B24: =IF(B7>=Assumptions!B40,Assumptions!B41,0) -> 0 | C24: =IF(C7>=Assumptions!B40,Assumptions!B41,0) -> 0 | D24: =IF(D7>=Assumptions!B40,Assumptions!B41,0) -> 0 | E24: =IF(E7>=Assumptions!B40,Assumptions!B41,0) -> 0 | F24: =IF(F7>=Assumptions!B40,Assumptions!B41,0) -> 0 | G24: =IF(G7>=Assumptions!B40,Assumptions!B41,0) -> 0 | H24: =IF(H7>=Assumptions!B40,Assumptions!B41,0) -> 0 | I24: =IF(I7>=Assumptions!B40,Assumptions!B41,0) -> 0 | J24: =IF(J7>=Assumptions!B40,Assumptions!B41,0) -> 0 | K24: =IF(K7>=Assumptions!B40,Assumptions!B41,0) -> 4500 | L24: =IF(L7>=Assumptions!B40,Assumptions!B41,0) -> 4500 | M24: =IF(M7>=Assumptions!B40,Assumptions!B41,0) -> 4500 | N24: =IF(N7>=Assumptions!B40,Assumptions!B41,0) -> 4500 | O24: =IF(O7>=Assumptions!B40,Assumptions!B41,0) -> 4500 | P24: =IF(P7>=Assumptions!B40,Assumptions!B41,0) -> 4500 | Q24: =IF(Q7>=Assumptions!B40,Assumptions!B41,0) -> 4500 | R24: =IF(R7>=Assumptions!B40,Assumptions!B41,0) -> 4500 | S24: =IF(S7>=Assumptions!B40,Assumptions!B41,0) -> 4500 | T24: =IF(T7>=Assumptions!B40,Assumptions!B41,0) -> 4500 | U24: =IF(U7>=Assumptions!B40,Assumptions!B41,0) -> 4500 | V24: =IF(V7>=Assumptions!B40,Assumptions!B41,0) -> 4500 | W24: =IF(W7>=Assumptions!B40,Assumptions!B41,0) -> 4500 | X24: =IF(X7>=Assumptions!B40,Assumptions!B41,0) -> 4500 | Y24: =IF(Y7>=Assumptions!B40,Assumptions!B41,0) -> 4500 | Z24: =IF(Z7>=Assumptions!B40,Assumptions!B41,0) -> 4500 | AA24: =IF(AA7>=Assumptions!B40,Assumptions!B41,0) -> 4500 | AB24: =IF(AB7>=Assumptions!B40,Assumptions!B41,0) -> 4500 | AC24: =IF(AC7>=Assumptions!B40,Assumptions!B41,0) -> 4500 | AD24: =IF(AD7>=Assumptions!B40,Assumptions!B41,0) -> 4500 | AE24: =IF(AE7>=Assumptions!B40,Assumptions!B41,0) -> 4500 | AF24: =IF(AF7>=Assumptions!B40,Assumptions!B41,0) -> 4500 | AG24: =IF(AG7>=Assumptions!B40,Assumptions!B41,0) -> 4500 | AH24: =IF(AH7>=Assumptions!B40,Assumptions!B41,0) -> 4500 | AI24: =IF(AI7>=Assumptions!B40,Assumptions!B41,0) -> 4500 | AJ24: =IF(AJ7>=Assumptions!B40,Assumptions!B41,0) -> 4500 | AK24: =IF(AK7>=Assumptions!B40,Assumptions!B41,0) -> 4500
A25: Total OpEx (£) | B25: =B23+B24 -> 0 | C25: =C23+C24 -> 0 | D25: =D23+D24 -> 0 | E25: =E23+E24 -> 0 | F25: =F23+F24 -> 0 | G25: =G23+G24 -> 0 | H25: =H23+H24 -> 0 | I25: =I23+I24 -> 0 | ... AK25: =AK23+AK24 -> 9500
A26: §5 OPERATING PROFIT
A27: Monthly operating profit/(loss) (£) | B27: =B20-B25 -> 44.38 | C27: =C20-C25 -> 165.56 | D27: =D20-D25 -> 298.12 | E27: =E20-E25 -> 441.26 | F27: =F20-F25 -> 595.78 | G27: =G20-G25 -> 794.22 | H27: =H20-H25 -> 1036.58 | I27: =I20-I25 -> 1290.32 | ... AK27: =AK20-AK25 -> 165094.32
A28: Cumulative (£) | B28: =B27 -> 44.38 | C28: =B28+C27 -> 209.94 | D28: =C28+D27 -> 508.06 | E28: =D28+E27 -> 949.32 | F28: =E28+F27 -> 1545.1 | G28: =F28+G27 -> 2339.32 | H28: =G28+H27 -> 3375.9 | I28: =H28+I27 -> 4666.22 | J28: =I28+J27 -> 6276.16 | ... AK28: =AJ28+AK27 -> 947722.4
A29: §6 MILESTONES
A30: ARR as % of £2.1M target | B30: =IFERROR(B14/Assumptions!B44,0) -> 0.00061714286 | C30: =IFERROR(C14/Assumptions!B44,0) -> 0.0013714286 | D30: =IFERROR(D14/Assumptions!B44,0) -> 0.0021942857 | E30: =IFERROR(E14/Assumptions!B44,0) -> 0.0030857143 | F30: =IFERROR(F14/Assumptions!B44,0) -> 0.0040457143 | G30: =IFERROR(G14/Assumptions!B44,0) -> 0.00528 | H30: =IFERROR(H14/Assumptions!B44,0) -> 0.0067885714 | I30: =IFERROR(I14/Assumptions!B44,0) -> 0.0083657143 | J30: =IFERROR(J14/Assumptions!B44,0) -> 0.010354286 | K30: =IFERROR(K14/Assumptions!B44,0) -> 0.012617143 | L30: =IFERROR(L14/Assumptions!B44,0) -> 0.015291429 | M30: =IFERROR(M14/Assumptions!B44,0) -> 0.018514286 | N30: =IFERROR(N14/Assumptions!B44,0) -> 0.022217143 | O30: =IFERROR(O14/Assumptions!B44,0) -> 0.026674286 | P30: =IFERROR(P14/Assumptions!B44,0) -> 0.031817143 | Q30: =IFERROR(Q14/Assumptions!B44,0) -> 0.03792 | R30: =IFERROR(R14/Assumptions!B44,0) -> 0.045051429 | S30: =IFERROR(S14/Assumptions!B44,0) -> 0.053417143 | T30: =IFERROR(T14/Assumptions!B44,0) -> 0.063291429 | U30: =IFERROR(U14/Assumptions!B44,0) -> 0.075017143 | V30: =IFERROR(V14/Assumptions!B44,0) -> 0.088868571 | W30: =IFERROR(W14/Assumptions!B44,0) -> 0.10505143 | X30: =IFERROR(X14/Assumptions!B44,0) -> 0.12418286 | Y30: =IFERROR(Y14/Assumptions!B44,0) -> 0.14688 | Z30: =IFERROR(Z14/Assumptions!B44,0) -> 0.17369143 | AA30: =IFERROR(AA14/Assumptions!B44,0) -> 0.20537143 | AB30: =IFERROR(AB14/Assumptions!B44,0) -> 0.24281143 | AC30: =IFERROR(AC14/Assumptions!B44,0) -> 0.28697143 | AD30: =IFERROR(AD14/Assumptions!B44,0) -> 0.33908571 | AE30: =IFERROR(AE14/Assumptions!B44,0) -> 0.40066286 | AF30: =IFERROR(AF14/Assumptions!B44,0) -> 0.47334857 | AG30: =IFERROR(AG14/Assumptions!B44,0) -> 0.55899429 | AH30: =IFERROR(AH14/Assumptions!B44,0) -> 0.66006857 | AI30: =IFERROR(AI14/Assumptions!B44,0) -> 0.77945143 | AJ30: =IFERROR(AJ14/Assumptions!B44,0) -> 0.92029714 | AK30: =IFERROR(AK14/Assumptions!B44,0) -> 1.0863086
A31: Break-even this month? | B31: =IF(B27>0,"Yes","-") -> Yes | C31: =IF(C27>0,"Yes","-") -> Yes | D31: =IF(D27>0,"Yes","-") -> Yes | E31: =IF(E27>0,"Yes","-") -> Yes | F31: =IF(F27>0,"Yes","-") -> Yes | G31: =IF(G27>0,"Yes","-") -> Yes | H31: =IF(H27>0,"Yes","-") -> Yes | I31: =IF(I27>0,"Yes","-") -> Yes | ... AK31: =IF(AK27>0,"Yes","-") -> Yes

Sheet Sensitivity
A1: SENSITIVITY — Subscribers & ARR at Month 36 under varying acquisition growth & churn
A2: Static table. All scenarios: M1 acquisition = 5, 80/20 PM/CP split. GREEN = hits £2.1M ARR target. AMBER = £1M+. RED = below £1M.
A4: SUBS AT M36 Churn ↓ / Acq growth → | B4: Acq +14%/mo | C4: Acq +16%/mo | D4: Acq +18%/mo ← BASE | E4: Acq +20%/mo | F4: Acq +25%/mo
A5: Churn 1%/mo | B5: 3918 | C5: 6355 | D5: 9717 | E5: 15755 | F5: 61598
A6: Churn 2%/mo | B6: 3679 | C6: 6008 | D6: 9236 | E6: 15042 | F6: 59321
A7: Churn 3%/mo | B7: 3469 | C7: 5698 | D7: 8801 | E7: 14392 | F7: 57203
A8: Churn 4%/mo | B8: 3278 | C8: 5414 | D8: 8403 | E8: 13792 | F8: 55235
A9: Churn 5%/mo | B9: 3108 | C9: 5160 | D9: 8041 | E9: 13241 | F9: 53395
A12: ARR AT MONTH 36 (£)
A13: ARR (£) AT M36 Churn ↓ / Acq growth → | B13: Acq +14%/mo | C13: Acq +16%/mo | D13: Acq +18%/mo ← BASE | E13: Acq +20%/mo | F13: Acq +25%/mo
A14: Churn 1%/mo | B14: 1015545.6 | C14: 1647216 | D14: 2518646.4 | E14: 4083696 | F14: 15966202
A15: Churn 2%/mo | B15: 953596.8 | C15: 1557273.6 | D15: 2393971.2 | E15: 3898886.4 | F15: 15376003
A16: Churn 3%/mo | B16: 899164.8 | C16: 1476921.6 | D16: 2281219.2 | E16: 3730406.4 | F16: 14827018
A17: Churn 4%/mo | B17: 849657.6 | C17: 1403308.8 | D17: 2178057.6 | E17: 3574886.4 | F17: 14316912
A18: Churn 5%/mo | B18: 805593.6 | C18: 1337472 | D18: 2084227.2 | E18: 3432067.2 | F18: 13839984
